secded_dec16.vhd
-------------------------------------------------------
--! @secded_dec16.vhd
--! @brief Descrição do decodificador de Hamming(22,16)
--! @author Tiago M Lucio (tiagolucio@usp.br)
--! @date 2022-07-20
-------------------------------------------------------

library ieee;
use ieee.numeric_bit.all;

entity secded_dec16 is
    port (
        mem_data: in bit_vector(21 downto 0);
        u_data: out bit_vector(15 downto 0);
        syndrome: out natural;
        two_errors: out bit;
        one_error: out bit
    );
end entity;

architecture arch of secded_dec16 is

    signal c0, c1, c2, c3, c4, c5 : bit;
    signal aux: bit_vector(15 downto 0);
    signal data: bit_vector(21 downto 0);

begin

    aux <= mem_data(20 downto 16) & mem_data(14 downto 8) & mem_data(6 downto 4) & mem_data(2);

    c0 <= mem_data(0) xor aux(15) xor aux(13) xor aux(11) xor aux(10) xor aux(8) xor aux(6) xor aux(4) xor aux(3) xor aux(1) xor aux(0);
    c1 <= mem_data(1) xor aux(13) xor aux(12) xor aux(10) xor aux(9) xor aux(6) xor aux(5) xor aux(3) xor aux(2) xor aux(0);
    c2 <= mem_data(3) xor aux(15) xor aux(14) xor aux(10) xor aux(9) xor aux(8) xor aux(7) xor aux(3) xor aux(2) xor aux(1);
    c3 <= mem_data(7) xor aux(10) xor aux(9) xor aux(8) xor aux(7) xor aux(6) xor aux(5) xor aux(4);
    c4 <= mem_data(15) xor aux(15) xor aux(14) xor aux(13) xor aux(12) xor aux(11);
    c5 <= mem_data(21) xor mem_data(0) xor mem_data(1) xor mem_data(3) xor mem_data(7) xor mem_data(15) xor 
        aux(15) xor aux(14) xor aux(13) xor aux(12) xor aux(11) xor aux(10) xor aux(9) xor aux(8) xor 
        aux(7) xor aux(6) xor aux(5) xor aux(4) xor aux(3) xor aux(2) xor aux(1) xor aux(0);

    one_error <= c5;
    two_errors <= (c4 or c3 or c2 or c1 or c0) and (not c5);
    
    error_correction : for i in 0 to 21 generate
        data(i) <= not mem_data(i) when ((c4 & c3 & c2 & c1 & c0) = to_unsigned(i + 1, 5)) else mem_data(i);
    end generate ; -- error_correction
    
    u_data <= data(20 downto 16) & data(14 downto 8) & data(6 downto 4) & data(2);

end arch ; -- arch

secded_enc16.vhd
-------------------------------------------------------
--! @secded_enc16.vhd
--! @brief Descrição do codificador de Hamming(22,16)
--! @author Tiago M Lucio (tiagolucio@usp.br)
--! @date 2022-07-20
-------------------------------------------------------

library ieee;
use ieee.numeric_bit.all;

entity secded_enc16 is
    port (
        u_data: in bit_vector(15 downto 0);
        mem_data: out bit_vector(21 downto 0)
    );
end entity;

architecture arch of secded_enc16 is

    signal p0, p1, p2, p3, p4, p5 : bit;

begin

    p0 <= u_data(15) xor u_data(13) xor u_data(11) xor u_data(10) xor u_data(8) xor u_data(6) xor u_data(4) xor u_data(3) xor u_data(1) xor u_data(0);
    p1 <= u_data(13) xor u_data(12) xor u_data(10) xor u_data(9) xor u_data(6) xor u_data(5) xor u_data(3) xor u_data(2) xor u_data(0);
    p2 <= u_data(15) xor u_data(14) xor u_data(10) xor u_data(9) xor u_data(8) xor u_data(7) xor u_data(3) xor u_data(2) xor u_data(1);
    p3 <= u_data(10) xor u_data(9) xor u_data(8) xor u_data(7) xor u_data(6) xor u_data(5) xor u_data(4);
    p4 <=  u_data(15) xor u_data(14) xor u_data(13) xor u_data(12) xor u_data(11);
    p5 <= p0 xor p1 xor p2 xor p3 xor p4 xor 
        u_data(15) xor u_data(14) xor u_data(13) xor u_data(12) xor u_data(11) xor u_data(10) xor u_data(9) xor u_data(8) xor 
        u_data(7) xor u_data(6) xor u_data(5) xor u_data(4) xor u_data(3) xor u_data(2) xor u_data(1) xor u_data(0);

    mem_data <= p5 & u_data(15 downto 11) & p4 & u_data(10 downto 4) & p3 & u_data(3 downto 1) & p2 & u_data(0) & p1 & p0;

end arch ; -- arch

secded_dec16_tb.vhd
-------------------------------------------------------
--! @secded_dec16_tb.vhd
--! @brief Descrição do Testbench codificador de Hamming(22,16)
--! @author Tiago M Lucio (tiagolucio@usp.br)
--! @date 2022-07-20
-------------------------------------------------------

library ieee;
use ieee.numeric_bit.all;

entity secded_dec16_tb is
end entity;

architecture test of secded_dec16_tb is
    component secded_enc16 is
        port (
            u_data: in bit_vector(15 downto 0);
            mem_data: out bit_vector(21 downto 0)
        );
    end component;

    component secded_dec16 is
        port (
            mem_data: in bit_vector(21 downto 0);
            u_data: out bit_vector(15 downto 0);
            syndrome: out natural;
            two_errors: out bit;
            one_error: out bit
        );
    end component;

    signal data_i, data_o: bit_vector(15 downto 0);
    signal mem_data_i, mem_data_o: bit_vector(21 downto 0);
    signal two_errors: bit;
    signal one_error: bit;

begin
    enc: secded_enc16
        port map (data_i, mem_data_o);
    dec: secded_dec16
        port map (mem_data_i, data_o, open, two_errors, one_error);

    process 
    type pattern_array is array (integer range<>) of integer;
    constant patterns : pattern_array :=
      (
        0,
        1,
        2,
        4,
        5,
        8,
        16,
        32,
        50,
        64,
        83,
        101,
        128,
        200,
        500,
        732,
        1000,
        1024,
        2342,
        5231,
        8342,
        13245,
        23542,
        35535,
        40000,
        51234,
        65534,
        65535
      );
    begin
        report "BOT";

        for i in patterns'range loop
            wait for 1 ns;
            data_i <= bit_vector(to_unsigned(patterns(i), 16));

            wait for 1 ns;

            mem_data_i <= mem_data_o;
      
            wait for 1 ns;
            assert data_o = data_i and one_error = '0' and two_errors = '0'
                report "Deu ruim :(" & LF &
                    HT & "entrada: " & integer'image(patterns(i)) & LF &
                    HT & "esperado: data_o =" & integer'image(patterns(i)) & " one_error = '0' e two_erros = '0'" & LF &
                    HT & "obtido  : data_o =" & integer'image(to_integer(unsigned(data_o))) & " one_error = " & bit'image(one_error) & " e two_erros = " & bit'image(two_errors) & LF;

            wait for 1 ns;
            mem_data_i(i mod 22) <= not mem_data_i(i mod 22);

            wait for 1 ns;
            assert data_i = data_o and one_error = '1' and two_errors = '0'
                report "Deu ruim :(" & LF &
                    HT & "entrada: " & integer'image(patterns(i)) & LF &
                    HT & "esperado: data_o =" & integer'image(patterns(i)) & " one_error = '0' e two_erros = '0'" & LF &
                    HT & "obtido  : data_o =" & integer'image(to_integer(unsigned(data_o))) & " one_error = " & bit'image(one_error) & " e two_erros = " & bit'image(two_errors) & LF;

            wait for 1 ns;
            mem_data_i((i + 5) mod 22) <= not mem_data_i((i + 5) mod 22);

            wait for 1 ns;
            assert one_error = '0' and two_errors = '1'
                report "Deu ruim :(" & LF &
                    HT & "entrada: " & integer'image(patterns(i)) & LF &
                    HT & "esperado: one_error = '0' e two_erros = '0'" & LF &
                    HT & "obtido  : one_error = " & bit'image(one_error) & " e two_erros = " & bit'image(two_errors) & LF;
        end loop; 
      
        report "EOF"; 
        wait;
    end process;

end architecture;

secded.vcd
$date
  Wed Jul 20 22:27:02 2022
$end
$version
  GHDL v0
$end
$timescale
  1 fs
$end
$scope module standard $end
$upscope $end
$scope module numeric_bit $end
$upscope $end
$scope module secded_dec16_tb $end
$var reg 16 ! data_i[15:0] $end
$var reg 16 " data_o[15:0] $end
$var reg 22 # mem_data_i[21:0] $end
$var reg 22 $ mem_data_o[21:0] $end
$var reg 1 % two_errors $end
$var reg 1 & one_error $end
$scope module enc $end
$var reg 16 ' u_data[15:0] $end
$var reg 22 ( mem_data[21:0] $end
$var reg 1 ) p0 $end
$var reg 1 * p1 $end
$var reg 1 + p2 $end
$var reg 1 , p3 $end
$var reg 1 - p4 $end
$var reg 1 . p5 $end
$upscope $end
$scope module dec $end
$var reg 22 / mem_data[21:0] $end
$var reg 16 0 u_data[15:0] $end
$var integer 32 1 syndrome $end
$var reg 1 2 two_errors $end
$var reg 1 3 one_error $end
$var reg 1 4 c0 $end
$var reg 1 5 c1 $end
$var reg 1 6 c2 $end
$var reg 1 7 c3 $end
$var reg 1 8 c4 $end
$var reg 1 9 c5 $end
$var reg 16 : aux[15:0] $end
$var reg 22 ; data[21:0] $end
$scope module error_correction(0) $end
$upscope $end
$scope module error_correction(1) $end
$upscope $end
$scope module error_correction(2) $end
$upscope $end
$scope module error_correction(3) $end
$upscope $end
$scope module error_correction(4) $end
$upscope $end
$scope module error_correction(5) $end
$upscope $end
$scope module error_correction(6) $end
$upscope $end
$scope module error_correction(7) $end
$upscope $end
$scope module error_correction(8) $end
$upscope $end
$scope module error_correction(9) $end
$upscope $end
$scope module error_correction(10) $end
$upscope $end
$scope module error_correction(11) $end
$upscope $end
$scope module error_correction(12) $end
$upscope $end
$scope module error_correction(13) $end
$upscope $end
$scope module error_correction(14) $end
$upscope $end
$scope module error_correction(15) $end
$upscope $end
$scope module error_correction(16) $end
$upscope $end
$scope module error_correction(17) $end
$upscope $end
$scope module error_correction(18) $end
$upscope $end
$scope module error_correction(19) $end
$upscope $end
$scope module error_correction(20) $end
$upscope $end
$scope module error_correction(21) $end
$upscope $end
$upscope $end
$upscope $end
$enddefinitions $end
#0
b0000000000000000 !
b0000000000000000 "
b0000000000000000000000 #
b0000000000000000000000 $
0%
0&
b0000000000000000 '
b0000000000000000000000 (
0)
0*
0+
0,
0-
0.
b0000000000000000000000 /
b0000000000000000 0
b0 1
02
03
04
05
06
07
08
09
b0000000000000000 :
b0000000000000000000000 ;
#1000000
#2000000
#3000000
#4000000
b0000000000000000 "
b0100000000000000000000 #
1&
b0100000000000000000000 /
b0000000000000000 0
13
14
16
18
19
b1000000000000000 :
b0000000000000000000000 ;
#5000000
#6000000
b1000100000000000 "
b0100000000000000001000 #
1%
0&
b0100000000000000001000 /
b1000100000000000 0
12
03
06
09
b0100010000000000001000 ;
#7000000
#8000000
b0000000000000001 !
b1000000000000000000111 $
b0000000000000001 '
b1000000000000000000111 (
1)
1*
1.
#9000000
b0000000000000001 "
b1000000000000000000111 #
0%
b1000000000000000000111 /
b0000000000000001 0
02
04
05
06
08
b0000000000000001 :
b1000000000000000000111 ;
#10000000
#11000000
b0000000000000000000111 #
1&
b0000000000000000000111 /
13
19
b0000000000000000000111 ;
#12000000
#13000000
b0000000000000001 "
b0000000000000000010111 #
1%
0&
b0000000000000000010111 /
b0000000000000001 0
12
03
14
16
09
b0000000000000011 :
b0000000000000000000111 ;
#14000000
#15000000
b0000000000000010 !
b1000000000000000011001 $
b0000000000000010 '
b1000000000000000011001 (
0*
1+
#16000000
b0000000000000010 "
b1000000000000000011001 #
0%
0&
b1000000000000000011001 /
b0000000000000010 0
02
03
04
05
06
09
b0000000000000010 :
b1000000000000000011001 ;
#17000000
#18000000
b1000000000000000011000 #
1&
b1000000000000000011000 /
13
14
19
b1000000000000000011001 ;
#19000000
#20000000
b0000000000001110 "
b1000000000000000111000 #
1%
0&
b1000000000000000111000 /
b0000000000001110 0
12
03
15
16
09
b0000000000000110 :
b1000000000000001111000 ;
#21000000
#22000000
b0000000000000100 !
b1000000000000000101010 $
b0000000000000100 '
b1000000000000000101010 (
0)
1*
#23000000
b0000000000000100 "
b1000000000000000101010 #
0%
0&
b1000000000000000101010 /
b0000000000000100 0
02
03
04
05
06
09
b0000000000000100 :
b1000000000000000101010 ;
#24000000
#25000000
b1000000000000000101000 #
1&
b1000000000000000101000 /
13
15
19
b1000000000000000101010 ;
#26000000
#27000000
b0000000000001110 "
b1000000000000001101000 #
1%
0&
b1000000000000001101000 /
b0000000000001110 0
12
03
14
05
16
09
b0000000000001100 :
b1000000000000001111000 ;
#28000000
#29000000
b0000000000000101 !
b0000000000000000101101 $
b0000000000000101 '
b0000000000000000101101 (
1)
0*
0.
#30000000
b0000000000000101 "
b0000000000000000101101 #
0%
b0000000000000000101101 /
b0000000000000101 0
02
04
06
b0000000000000101 :
b0000000000000000101101 ;
#31000000
#32000000
b0000000000000101 "
b0000000000000000101001 #
1&
b0000000000000000101001 /
b0000000000000101 0
13
14
15
19
b0000000000000100 :
b0000000000000000101101 ;
#33000000
#34000000
b0000000001000100 "
b0000000000000010101001 #
1%
0&
b0000000000000010101001 /
b0000000001000100 0
12
03
17
09
b0000000000010010101001 ;
#35000000
#36000000
b0000000000001000 !
b0000000000000001001011 $
b0000000000001000 '
b0000000000000001001011 (
1*
0.
#37000000
b0000000000001000 "
b0000000000000001001011 #
0%
b0000000000000001001011 /
b0000000000001000 0
02
04
05
07
b0000000000001000 :
b0000000000000001001011 ;
#38000000
#39000000
b0000000000000001000011 #
1&
b0000000000000001000011 /
13
16
19
b0000000000000001001011 ;
#40000000
#41000000
b0000000100011000 "
b0000000000000101000011 #
1%
0&
b0000000000000101000011 /
b0000000100011000 0
12
03
14
17
09
b0000000000011000 :
b0000000001000101000011 ;
#42000000
#43000000
b0000000000010000 !
b1000000000000110000001 $
b0000000000010000 '
b1000000000000110000001 (
0*
0+
1,
1.
#44000000
b0000000000010000 "
b1000000000000110000001 #
0%
0&
b1000000000000110000001 /
b0000000000010000 0
02
03
04
05
06
07
09
b0000000000010000 :
b1000000000000110000001 ;
#45000000
#46000000
b0000000000010000 "
b1000000000000110010001 #
1&
b1000000000000110010001 /
b0000000000010000 0
13
14
16
19
b0000000000010010 :
b1000000000000110000001 ;
#47000000
#48000000
b0000010000110010 "
b1000000000001110010001 #
1%
0&
b1000000000001110010001 /
b0000010000110010 0
12
03
15
17
09
b0000000000110010 :
b1000000100001110010001 ;
#49000000
#50000000
b0000000000100000 !
b1000000000001010000010 $
b0000000000100000 '
b1000000000001010000010 (
0)
1*
#51000000
b0000000000100000 "
b1000000000001010000010 #
0%
b1000000000001010000010 /
b0000000000100000 0
02
04
05
06
07
b0000000000100000 :
b1000000000001010000010 ;
#52000000
#53000000
b0000000000100000 "
b1000000000001010100010 #
1&
b1000000000001010100010 /
b0000000000100000 0
13
15
16
19
b0000000000100100 :
b1000000000001010000010 ;
#54000000
#55000000
b0000000101100100 "
b1000000000011010100010 #
1%
0&
b1000000000011010100010 /
b0000000101100100 0
12
03
14
05
17
09
b0000000001100100 :
b1000000001011010100010 ;
#56000000
#57000000
b0000000000110010 !
b1000000000001100011010 $
b0000000000110010 '
b1000000000001100011010 (
1+
0,
#58000000
b0000000000110010 "
b1000000000001100011010 #
0%
b1000000000001100011010 /
b0000000000110010 0
02
04
06
07
b0000000000110010 :
b1000000000001100011010 ;
#59000000
#60000000
b0000000000110010 "
b1000000000001101011010 #
1&
b1000000000001101011010 /
b0000000000110010 0
13
14
15
16
19
b0000000000111010 :
b1000000000001100011010 ;
#61000000
#62000000
b0000000011111010 "
b1000000000101101011010 #
1%
0&
b1000000000101101011010 /
b0000000011111010 0
12
03
06
17
09
b0000000010111010 :
b1000000000111101011010 ;
#63000000
#64000000
b0000000001000000 !
b0000000000010010000011 $
b0000000001000000 '
b0000000000010010000011 (
1)
0+
1,
0.
#65000000
b0000000001000000 "
b0000000000010010000011 #
0%
b0000000000010010000011 /
b0000000001000000 0
02
04
05
06
07
b0000000001000000 :
b0000000000010010000011 ;
#66000000
#67000000
b0000000000010000000011 #
1&
b0000000000010000000011 /
13
17
19
b0000000000010010000011 ;
#68000000
#69000000
b0000000101000010 "
b0000000001010000000011 #
1%
0&
b0000000001010000000011 /
b0000000101000010 0
12
03
14
16
07
09
b0000000101000000 :
b0000000001010000010011 ;
#70000000
#71000000
b0000000001010011 !
b1000000000010100011100 $
b0000000001010011 '
b1000000000010100011100 (
0)
0*
1+
0,
1.
#72000000
b0000000001010011 "
b1000000000010100011100 #
0%
b1000000000010100011100 /
b0000000001010011 0
02
04
05
06
b0000000001010011 :
b1000000000010100011100 ;
#73000000
#74000000
b0000000001010011 "
b1000000000010000011100 #
1&
b1000000000010000011100 /
b0000000001010011 0
13
14
17
19
b0000000001000011 :
b1000000000010100011100 ;
#75000000
#76000000
b0000001001001011 "
b1000000010010000011100 #
1%
0&
b1000000010010000011100 /
b0000001001001011 0
12
03
15
16
07
09
b0000001001000011 :
b1000000010010001011100 ;
#77000000
#78000000
b0000000001100101 !
b1000000000011000101100 $
b0000000001100101 '
b1000000000011000101100 (
#79000000
b0000000001100101 "
b1000000000011000101100 #
0%
b1000000000011000101100 /
b0000000001100101 0
02
04
05
06
b0000000001100101 :
b1000000000011000101100 ;
#80000000
#81000000
b0000000001100101 "
b1000000000010000101100 #
1&
b1000000000010000101100 /
b0000000001100101 0
13
15
17
19
b0000000001000101 :
b1000000000011000101100 ;
#82000000
#83000000
b0000010001000111 "
b1000000100010000101100 #
1%
0&
b1000000100010000101100 /
b0000010001000111 0
12
03
14
05
16
07
09
b0000010001000101 :
b1000000100010000111100 ;
#84000000
#85000000
b0000000010000000 !
b1000000000100010001000 $
b0000000010000000 '
b1000000000100010001000 (
1,
1.
#86000000
b0000000010000000 "
b1000000000100010001000 #
0%
0&
b1000000000100010001000 /
b0000000010000000 0
02
03
04
06
07
09
b0000000010000000 :
b1000000000100010001000 ;
#87000000
#88000000
b0000000010000000 "
b1000000000110010001000 #
1&
b1000000000110010001000 /
b0000000010000000 0
13
14
15
17
19
b0000000011000000 :
b1000000000100010001000 ;
#89000000
#90000000
b0000000011000000 "
b1000001000110010001000 #
1%
0&
b1000001000110010001000 /
b0000000011000000 0
12
03
18
09
b1000001000110010001000 ;
#91000000
#92000000
b0000000011001000 !
b1000000000110001000000 $
b0000000011001000 '
b1000000000110001000000 (
0+
0,
#93000000
b0000000011001000 "
b1000000000110001000000 #
0%
0&
b1000000000110001000000 /
b0000000011001000 0
02
03
04
05
06
07
08
09
b0000000011001000 :
b1000000000110001000000 ;
#94000000
#95000000
b0000000011001000 "
b1000000000010001000000 #
1&
b1000000000010001000000 /
b0000000011001000 0
13
16
17
19
b0000000001001000 :
b1000000000110001000000 ;
#96000000
#97000000
b0000100001001000 "
b1000010000010001000000 #
1%
0&
b1000010000010001000000 /
b0000100001001000 0
12
03
14
18
09
b0000100001001000 :
b1000010000010001000000 ;
#98000000
#99000000
b0000000111110100 !
b0000000001111110101011 $
b0000000111110100 '
b0000000001111110101011 (
1)
1*
1+
1,
0.
#100000000
b0000000111110100 "
b0000000001111110101011 #
0%
0&
b0000000001111110101011 /
b0000000111110100 0
02
03
04
05
06
07
08
09
b0000000111110100 :
b0000000001111110101011 ;
#101000000
#102000000
b0000000111110100 "
b0000000000111110101011 #
1&
b0000000000111110101011 /
b0000000111110100 0
13
14
16
17
19
b0000000011110100 :
b0000000001111110101011 ;
#103000000
#104000000
b0001000011110100 "
b0000100000111110101011 #
1%
0&
b0000100000111110101011 /
b0001000011110100 0
12
03
15
18
09
b0001000011110100 :
b0000100000111110101011 ;
#105000000
#106000000
b0000001011011100 !
b1000000010110101100001 $
b0000001011011100 '
b1000000010110101100001 (
0*
0+
0,
1.
#107000000
b0000001011011100 "
b1000000010110101100001 #
0%
b1000000010110101100001 /
b0000001011011100 0
02
04
05
06
07
08
b0000001011011100 :
b1000000010110101100001 ;
#108000000
#109000000
b0000001011011100 "
b1000000000110101100001 #
1&
b1000000000110101100001 /
b0000001011011100 0
13
15
16
17
19
b0000000011011100 :
b1000000010110101100001 ;
#110000000
#111000000
b0010000011011100 "
b1001000000110101100001 #
1%
0&
b1001000000110101100001 /
b0010000011011100 0
12
03
14
05
18
09
b0010000011011100 :
b1001000000110101100001 ;
#112000000
#113000000
b0000001111101000 !
b0000000011111011000001 $
b0000001111101000 '
b0000000011111011000001 (
1,
0.
#114000000
b0000001111101000 "
b0000000011111011000001 #
0%
b0000000011111011000001 /
b0000001111101000 0
02
04
06
07
08
b0000001111101000 :
b0000000011111011000001 ;
#115000000
#116000000
b0000001111101000 "
b0000000111111011000001 #
1&
b0000000111111011000001 /
b0000001111101000 0
13
14
15
16
17
19
b0000011111101000 :
b0000000011111011000001 ;
#117000000
#118000000
b0100011111101000 "
b0010000111111011000001 #
1%
0&
b0010000111111011000001 /
b0100011111101000 0
12
03
06
18
09
b0100011111101000 :
b0010000111111011000001 ;
#119000000
#120000000
b0000010000000000 !
b1000000100000010001011 $
b0000010000000000 '
b1000000100000010001011 (
1*
1+
1.
#121000000
b0000010000000000 "
b1000000100000010001011 #
0%
0&
b1000000100000010001011 /
b0000010000000000 0
02
03
04
05
06
07
08
09
b0000010000000000 :
b1000000100000010001011 ;
#122000000
#123000000
b1000001100000010001011 #
1&
b1000001100000010001011 /
13
18
19
b1000000100000010001011 ;
#124000000
#125000000
b1000010000000010 "
b1100001100000010001011 #
1%
0&
b1100001100000010001011 /
b1000010000000010 0
12
03
14
16
08
09
b1000010000000000 :
b1100001100000010011011 ;
#126000000
#127000000
b0000100100100110 !
b0000011001001000111001 $
b0000100100100110 '
b0000011001001000111001 (
0*
0,
1-
0.
#128000000
b0000100100100110 "
b0000011001001000111001 #
0%
0&
b0000011001001000111001 /
b0000100100100110 0
02
03
04
05
06
07
09
b0000100100100110 :
b0000011001001000111001 ;
#129000000
#130000000
b0000100100100110 "
b0000001001001000111001 #
1&
b0000001001001000111001 /
b0000100100100110 0
13
14
18
19
b0000000100100110 :
b0000011001001000111001 ;
#131000000
#132000000
b1000001001001000111001 #
1%
0&
b1000001001001000111001 /
12
03
09
b1000011001001000111001 ;
#133000000
#134000000
b0001010001101111 !
b0000101100011011110111 $
b0001010001101111 '
b0000101100011011110111 (
1*
0+
1,
0.
#135000000
b0001010001101111 "
b0000101100011011110111 #
0%
b0000101100011011110111 /
b0001010001101111 0
02
04
05
06
07
08
b0001010001101111 :
b0000101100011011110111 ;
#136000000
#137000000
b0001010001101111 "
b0000001100011011110111 #
1&
b0000001100011011110111 /
b0001010001101111 0
13
15
18
19
b0000010001101111 :
b0000101100011011110111 ;
#138000000
#139000000
b0010010001101111 "
b0000001100011011110110 #
1%
0&
b0000001100011011110110 /
b0010010001101111 0
12
03
14
09
b0001001100011011110110 ;
#140000000
#141000000
b0010000010010110 !
b0001001000100100111001 $
b0010000010010110 '
b0001001000100100111001 (
0*
1+
0,
0.
#142000000
b0010000010010110 "
b0001001000100100111001 #
0%
b0001001000100100111001 /
b0010000010010110 0
02
04
05
06
07
08
b0010000010010110 :
b0001001000100100111001 ;
#143000000
#144000000
b0010000010010110 "
b0000001000100100111001 #
1&
b0000001000100100111001 /
b0010000010010110 0
13
14
15
18
19
b0000000010010110 :
b0001001000100100111001 ;
#145000000
#146000000
b0000100010010110 "
b0000001000100100111011 #
1%
0&
b0000001000100100111011 /
b0000100010010110 0
12
03
05
09
b0000011000100100111011 ;
#147000000
#148000000
b0011001110111101 !
b0001100011101111101111 $
b0011001110111101 '
b0001100011101111101111 (
1*
1,
0-
0.
#149000000
b0011001110111101 "
b0001100011101111101111 #
0%
b0001100011101111101111 /
b0011001110111101 0
02
04
07
08
b0011001110111101 :
b0001100011101111101111 ;
#150000000
#151000000
b0011001110111101 "
b0011100011101111101111 #
1&
b0011100011101111101111 /
b0011001110111101 0
13
16
18
19
b0111001110111101 :
b0001100011101111101111 ;
#152000000
#153000000
b0111001110111100 "
b0011100011101111101011 #
1%
0&
b0011100011101111101011 /
b0111001110111100 0
12
03
14
15
09
b0111001110111100 :
b0011100011101111101011 ;
#154000000
#155000000
b0101101111110110 !
b0010111011111100110011 $
b0101101111110110 '
b0010111011111100110011 (
0+
0,
1-
0.
#156000000
b0101101111110110 "
b0010111011111100110011 #
0%
0&
b0010111011111100110011 /
b0101101111110110 0
02
03
04
05
06
07
08
09
b0101101111110110 :
b0010111011111100110011 ;
#157000000
#158000000
b0101101111110110 "
b0110111011111100110011 #
1&
b0110111011111100110011 /
b0101101111110110 0
13
14
16
18
19
b1101101111110110 :
b0010111011111100110011 ;
#159000000
#160000000
b1101001111110110 "
b0110111011111100111011 #
1%
0&
b0110111011111100111011 /
b1101001111110110 0
12
03
06
09
b0110101011111100111011 ;
#161000000
#162000000
b1000101011001111 !
b1100010010110011110110 $
b1000101011001111 '
b1100010010110011110110 (
0)
1,
0-
1.
#163000000
b1000101011001111 "
b1100010010110011110110 #
0%
0&
b1100010010110011110110 /
b1000101011001111 0
02
03
04
06
07
08
09
b1000101011001111 :
b1100010010110011110110 ;
#164000000
#165000000
b0100010010110011110110 #
1&
b0100010010110011110110 /
13
19
b0100010010110011110110 ;
#166000000
#167000000
b1000101011001111 "
b0100010010110011100110 #
1%
0&
b0100010010110011100110 /
b1000101011001111 0
12
03
14
16
09
b1000101011001101 :
b0100010010110011110110 ;
#168000000
#169000000
b1001110001000000 !
b1100111100010000000010 $
b1001110001000000 '
b1100111100010000000010 (
0,
1-
#170000000
b1001110001000000 "
b1100111100010000000010 #
0%
0&
b1100111100010000000010 /
b1001110001000000 0
02
03
04
06
07
08
09
b1001110001000000 :
b1100111100010000000010 ;
#171000000
#172000000
b1100111100010000000011 #
1&
b1100111100010000000011 /
13
14
19
b1100111100010000000010 ;
#173000000
#174000000
b1001110001001100 "
b1100111100010000100011 #
1%
0&
b1100111100010000100011 /
b1001110001001100 0
12
03
15
16
09
b1001110001000100 :
b1100111100010001100011 ;
#175000000
#176000000
b1100100000100010 !
b0110011000001010011011 $
b1100100000100010 '
b0110011000001010011011 (
1)
1+
1,
0.
#177000000
b1100100000100010 "
b0110011000001010011011 #
0%
0&
b0110011000001010011011 /
b1100100000100010 0
02
03
04
05
06
07
09
b1100100000100010 :
b0110011000001010011011 ;
#178000000
#179000000
b0110011000001010011001 #
1&
b0110011000001010011001 /
13
15
19
b0110011000001010011011 ;
#180000000
#181000000
b1100100000101000 "
b0110011000001011011001 #
1%
0&
b0110011000001011011001 /
b1100100000101000 0
12
03
14
05
16
09
b1100100000101010 :
b0110011000001011001001 ;
#182000000
#183000000
b1111111111111110 !
b1111111111111111111001 $
b1111111111111110 '
b1111111111111111111001 (
0*
1.
#184000000
b1111111111111110 "
b1111111111111111111001 #
0%
0&
b1111111111111111111001 /
b1111111111111110 0
02
03
04
06
09
b1111111111111110 :
b1111111111111111111001 ;
#185000000
#186000000
b1111111111111110 "
b1111111111111111111101 #
1&
b1111111111111111111101 /
b1111111111111110 0
13
14
15
19
b1111111111111111 :
b1111111111111111111001 ;
#187000000
#188000000
b1111111110111111 "
b1111111111111101111101 #
1%
0&
b1111111111111101111101 /
b1111111110111111 0
12
03
17
09
b1111111111101101111101 ;
#189000000
#190000000
b1111111111111111 !
b0111111111111111111110 $
b1111111111111111 '
b0111111111111111111110 (
0)
1*
0.
#191000000
b1111111111111111 "
b0111111111111111111110 #
0%
b0111111111111111111110 /
b1111111111111111 0
02
04
05
07
b0111111111111111111110 ;
#192000000
#193000000
b0111111111111111110110 #
1&
b0111111111111111110110 /
13
16
19
b0111111111111111111110 ;
#194000000
#195000000
b1111111011101111 "
b0111111111111011110110 #
1%
0&
b0111111111111011110110 /
b1111111011101111 0
12
03
14
17
09
b1111111111101111 :
b0111111110111011110110 ;
